csv_export/__init__.py
csv_export/apps.py
csv_export/views.py
django_csv_export_view-2.0.1.data/data/CHANGELOG.md
django_csv_export_view-2.0.1.data/data/README.md
django_csv_export_view-2.0.1.dist-info/LICENSE
django_csv_export_view-2.0.1.dist-info/METADATA
django_csv_export_view-2.0.1.dist-info/WHEEL
django_csv_export_view-2.0.1.dist-info/top_level.txt
django_csv_export_view-2.0.1.dist-info/RECORD
